<?xml version="1.0" encoding="UTF-8"?>
<DEFECTS>
  <DEFECT>
    <SFA>
      <FILEPATH>C:\Users\chase\OneDrive\Documents\lvgl5.3sim\visual_studio_2017_sdl\lvgl\lv_objx\</FILEPATH>
      <FILENAME>lv_line.c</FILENAME>
      <LINE>262</LINE>
      <COLUMN>29</COLUMN>
    </SFA>
    <DEFECTCODE>6001</DEFECTCODE>
    <DESCRIPTION>Using uninitialized memory 'p2'.</DESCRIPTION>
    <FUNCTION>lv_line_design</FUNCTION>
    <DECORATED>lv_line_design</DECORATED>
    <FUNCLINE>207</FUNCLINE>
    <PROBABILITY>1</PROBABILITY>
    <RANK>3</RANK>
    <CATEGORY>
      <RULECATEGORY>mspft</RULECATEGORY>
    </CATEGORY>
    <PATH>
      <SFA>
        <FILEPATH>C:\Users\chase\OneDrive\Documents\lvgl5.3sim\visual_studio_2017_sdl\lvgl\lv_objx\</FILEPATH>
        <FILENAME>lv_line.c</FILENAME>
        <LINE>210</LINE>
        <COLUMN>12</COLUMN>
      </SFA>
      <SFA>
        <FILEPATH>C:\Users\chase\OneDrive\Documents\lvgl5.3sim\visual_studio_2017_sdl\lvgl\lv_objx\</FILEPATH>
        <FILENAME>lv_line.c</FILENAME>
        <LINE>211</LINE>
        <COLUMN>17</COLUMN>
      </SFA>
      <SFA>
        <FILEPATH>C:\Users\chase\OneDrive\Documents\lvgl5.3sim\visual_studio_2017_sdl\lvgl\lv_objx\</FILEPATH>
        <FILENAME>lv_line.c</FILENAME>
        <LINE>212</LINE>
        <COLUMN>24</COLUMN>
      </SFA>
      <SFA>
        <FILEPATH>C:\Users\chase\OneDrive\Documents\lvgl5.3sim\visual_studio_2017_sdl\lvgl\lv_objx\</FILEPATH>
        <FILENAME>lv_line.c</FILENAME>
        <LINE>214</LINE>
        <COLUMN>31</COLUMN>
      </SFA>
      <SFA>
        <FILEPATH>C:\Users\chase\OneDrive\Documents\lvgl5.3sim\visual_studio_2017_sdl\lvgl\lv_objx\</FILEPATH>
        <FILENAME>lv_line.c</FILENAME>
        <LINE>216</LINE>
        <COLUMN>21</COLUMN>
      </SFA>
      <SFA>
        <FILEPATH>C:\Users\chase\OneDrive\Documents\lvgl5.3sim\visual_studio_2017_sdl\lvgl\lv_objx\</FILEPATH>
        <FILENAME>lv_line.c</FILENAME>
        <LINE>217</LINE>
        <COLUMN>17</COLUMN>
      </SFA>
      <SFA>
        <FILEPATH>C:\Users\chase\OneDrive\Documents\lvgl5.3sim\visual_studio_2017_sdl\lvgl\lv_objx\</FILEPATH>
        <FILENAME>lv_line.c</FILENAME>
        <LINE>218</LINE>
        <COLUMN>18</COLUMN>
      </SFA>
      <SFA>
        <FILEPATH>C:\Users\chase\OneDrive\Documents\lvgl5.3sim\visual_studio_2017_sdl\lvgl\lv_objx\</FILEPATH>
        <FILENAME>lv_line.c</FILENAME>
        <LINE>219</LINE>
        <COLUMN>8</COLUMN>
      </SFA>
      <SFA>
        <FILEPATH>C:\Users\chase\OneDrive\Documents\lvgl5.3sim\visual_studio_2017_sdl\lvgl\lv_objx\</FILEPATH>
        <FILENAME>lv_line.c</FILENAME>
        <LINE>220</LINE>
        <COLUMN>19</COLUMN>
      </SFA>
      <SFA>
        <FILEPATH>C:\Users\chase\OneDrive\Documents\lvgl5.3sim\visual_studio_2017_sdl\lvgl\lv_objx\</FILEPATH>
        <FILENAME>lv_line.c</FILENAME>
        <LINE>221</LINE>
        <COLUMN>19</COLUMN>
      </SFA>
      <SFA>
        <FILEPATH>C:\Users\chase\OneDrive\Documents\lvgl5.3sim\visual_studio_2017_sdl\lvgl\lv_objx\</FILEPATH>
        <FILENAME>lv_line.c</FILENAME>
        <LINE>222</LINE>
        <COLUMN>19</COLUMN>
      </SFA>
      <SFA>
        <FILEPATH>C:\Users\chase\OneDrive\Documents\lvgl5.3sim\visual_studio_2017_sdl\lvgl\lv_objx\</FILEPATH>
        <FILENAME>lv_line.c</FILENAME>
        <LINE>223</LINE>
        <COLUMN>19</COLUMN>
        <KEYEVENT>
          <ID>1</ID>
          <KIND>declaration</KIND>
          <IMPORTANCE>Essential</IMPORTANCE>
          <MESSAGE>'p2' is not initialized</MESSAGE>
        </KEYEVENT>
      </SFA>
      <SFA>
        <FILEPATH>C:\Users\chase\OneDrive\Documents\lvgl5.3sim\visual_studio_2017_sdl\lvgl\lv_objx\</FILEPATH>
        <FILENAME>lv_line.c</FILENAME>
        <LINE>224</LINE>
        <COLUMN>19</COLUMN>
      </SFA>
      <SFA>
        <FILEPATH>C:\Users\chase\OneDrive\Documents\lvgl5.3sim\visual_studio_2017_sdl\lvgl\lv_objx\</FILEPATH>
        <FILENAME>lv_line.c</FILENAME>
        <LINE>225</LINE>
        <COLUMN>17</COLUMN>
      </SFA>
      <SFA>
        <FILEPATH>C:\Users\chase\OneDrive\Documents\lvgl5.3sim\visual_studio_2017_sdl\lvgl\lv_objx\</FILEPATH>
        <FILENAME>lv_line.c</FILENAME>
        <LINE>227</LINE>
        <COLUMN>19</COLUMN>
      </SFA>
      <SFA>
        <FILEPATH>C:\Users\chase\OneDrive\Documents\lvgl5.3sim\visual_studio_2017_sdl\lvgl\lv_objx\</FILEPATH>
        <FILENAME>lv_line.c</FILENAME>
        <LINE>228</LINE>
        <COLUMN>8</COLUMN>
      </SFA>
      <SFA>
        <FILEPATH>C:\Users\chase\OneDrive\Documents\lvgl5.3sim\visual_studio_2017_sdl\lvgl\lv_objx\</FILEPATH>
        <FILENAME>lv_line.c</FILENAME>
        <LINE>229</LINE>
        <COLUMN>33</COLUMN>
      </SFA>
      <SFA>
        <FILEPATH>C:\Users\chase\OneDrive\Documents\lvgl5.3sim\visual_studio_2017_sdl\lvgl\lv_objx\</FILEPATH>
        <FILENAME>lv_line.c</FILENAME>
        <LINE>230</LINE>
        <COLUMN>37</COLUMN>
      </SFA>
      <SFA>
        <FILEPATH>C:\Users\chase\OneDrive\Documents\lvgl5.3sim\visual_studio_2017_sdl\lvgl\lv_objx\</FILEPATH>
        <FILENAME>lv_line.c</FILENAME>
        <LINE>231</LINE>
        <COLUMN>37</COLUMN>
      </SFA>
      <SFA>
        <FILEPATH>C:\Users\chase\OneDrive\Documents\lvgl5.3sim\visual_studio_2017_sdl\lvgl\lv_objx\</FILEPATH>
        <FILENAME>lv_line.c</FILENAME>
        <LINE>232</LINE>
        <COLUMN>30</COLUMN>
      </SFA>
      <SFA>
        <FILEPATH>C:\Users\chase\OneDrive\Documents\lvgl5.3sim\visual_studio_2017_sdl\lvgl\lv_objx\</FILEPATH>
        <FILENAME>lv_line.c</FILENAME>
        <LINE>233</LINE>
        <COLUMN>18</COLUMN>
      </SFA>
      <SFA>
        <FILEPATH>C:\Users\chase\OneDrive\Documents\lvgl5.3sim\visual_studio_2017_sdl\lvgl\lv_objx\</FILEPATH>
        <FILENAME>lv_line.c</FILENAME>
        <LINE>236</LINE>
        <COLUMN>14</COLUMN>
      </SFA>
      <SFA>
        <FILEPATH>C:\Users\chase\OneDrive\Documents\lvgl5.3sim\visual_studio_2017_sdl\lvgl\lv_objx\</FILEPATH>
        <FILENAME>lv_line.c</FILENAME>
        <LINE>236</LINE>
        <COLUMN>21</COLUMN>
        <KEYEVENT>
          <ID>2</ID>
          <KIND>branch</KIND>
          <IMPORTANCE>Full</IMPORTANCE>
          <MESSAGE>Skip this loop, (assume 'i&lt;ext-&gt;point_num-1' is false)</MESSAGE>
        </KEYEVENT>
      </SFA>
      <SFA>
        <FILEPATH>C:\Users\chase\OneDrive\Documents\lvgl5.3sim\visual_studio_2017_sdl\lvgl\lv_objx\</FILEPATH>
        <FILENAME>lv_line.c</FILENAME>
        <LINE>261</LINE>
        <COLUMN>22</COLUMN>
        <KEYEVENT>
          <ID>3</ID>
          <KIND>branch</KIND>
          <IMPORTANCE>Full</IMPORTANCE>
          <MESSAGE>Enter this branch, (assume 'style-&gt;line.rounded')</MESSAGE>
        </KEYEVENT>
      </SFA>
      <SFA>
        <FILEPATH>C:\Users\chase\OneDrive\Documents\lvgl5.3sim\visual_studio_2017_sdl\lvgl\lv_objx\</FILEPATH>
        <FILENAME>lv_line.c</FILENAME>
        <LINE>262</LINE>
        <COLUMN>27</COLUMN>
      </SFA>
      <SFA>
        <FILEPATH>C:\Users\chase\OneDrive\Documents\lvgl5.3sim\visual_studio_2017_sdl\lvgl\lv_objx\</FILEPATH>
        <FILENAME>lv_line.c</FILENAME>
        <LINE>263</LINE>
        <COLUMN>27</COLUMN>
      </SFA>
      <SFA>
        <FILEPATH>C:\Users\chase\OneDrive\Documents\lvgl5.3sim\visual_studio_2017_sdl\lvgl\lv_objx\</FILEPATH>
        <FILENAME>lv_line.c</FILENAME>
        <LINE>264</LINE>
        <COLUMN>27</COLUMN>
      </SFA>
      <SFA>
        <FILEPATH>C:\Users\chase\OneDrive\Documents\lvgl5.3sim\visual_studio_2017_sdl\lvgl\lv_objx\</FILEPATH>
        <FILENAME>lv_line.c</FILENAME>
        <LINE>265</LINE>
        <COLUMN>27</COLUMN>
      </SFA>
      <SFA>
        <FILEPATH>C:\Users\chase\OneDrive\Documents\lvgl5.3sim\visual_studio_2017_sdl\lvgl\lv_objx\</FILEPATH>
        <FILENAME>lv_line.c</FILENAME>
        <LINE>266</LINE>
        <COLUMN>12</COLUMN>
      </SFA>
      <SFA>
        <FILEPATH>C:\Users\chase\OneDrive\Documents\lvgl5.3sim\visual_studio_2017_sdl\lvgl\lv_objx\</FILEPATH>
        <FILENAME>lv_line.c</FILENAME>
        <LINE>262</LINE>
        <COLUMN>29</COLUMN>
        <KEYEVENT>
          <ID>4</ID>
          <KIND>usage</KIND>
          <IMPORTANCE>Essential</IMPORTANCE>
          <MESSAGE>'p2' is used, but may not have been initialized</MESSAGE>
        </KEYEVENT>
      </SFA>
    </PATH>
  </DEFECT>
</DEFECTS>